MANIFEST.in
setup.py
src/fsqio/__init__.py
src/fsqio.pants.pom_resolve.egg-info/PKG-INFO
src/fsqio.pants.pom_resolve.egg-info/SOURCES.txt
src/fsqio.pants.pom_resolve.egg-info/dependency_links.txt
src/fsqio.pants.pom_resolve.egg-info/namespace_packages.txt
src/fsqio.pants.pom_resolve.egg-info/requires.txt
src/fsqio.pants.pom_resolve.egg-info/top_level.txt
src/fsqio.pants.pom_resolve.egg-info/zip-safe
src/fsqio/pants/__init__.py
src/fsqio/pants/pom_resolve/__init__.py
src/fsqio/pants/pom_resolve/coordinate.py
src/fsqio/pants/pom_resolve/dependency.py
src/fsqio/pants/pom_resolve/fetcher.py
src/fsqio/pants/pom_resolve/maven_dependency_graph.py
src/fsqio/pants/pom_resolve/maven_version.py
src/fsqio/pants/pom_resolve/pom.py
src/fsqio/pants/pom_resolve/pom_resolve.py
src/fsqio/pants/pom_resolve/register.py
src/fsqio/pants/pom_resolve/sort_projects.py